httpasync/__init__.py
httpasync/version.py
httpasync-0.2.0.dist-info/LICENSE
httpasync-0.2.0.dist-info/METADATA
httpasync-0.2.0.dist-info/WHEEL
httpasync-0.2.0.dist-info/top_level.txt
httpasync-0.2.0.dist-info/RECORD
