Metadata-Version: 2.1
Name: httpasync
Version: 0.2.0
Summary: HTTP Async.
Home-page: https://github.com/eerimoq/httpasync
Author: Erik Moqvist
Author-email: erik.moqvist@gmail.com
License: MIT
Keywords: http
Platform: UNKNOWN
Classifier: License :: OSI Approved :: MIT License
Classifier: Programming Language :: Python :: 3
Requires-Dist: httptools
